SimpleRDFServer.py
setup.py
SimpleRDFServer.egg-info/PKG-INFO
SimpleRDFServer.egg-info/SOURCES.txt
SimpleRDFServer.egg-info/dependency_links.txt
SimpleRDFServer.egg-info/top_level.txt
